{
  "address": "3qWdfedEMajVfoF7CgHvoCPy7Ddd7r1pWiHYGmbxQ3fj",
  "metadata": {
    "name": "anchor_order_matching",
    "version": "0.1.0",
    "spec": "0.1.0",
    "description": "Created with Anchor"
  },
  "instructions": [
    {
      "name": "initialize",
      "discriminator": [
        175,
        175,
        109,
        31,
        13,
        152,
        155,
        237
      ],
      "accounts": [
        {
          "name": "order_book",
          "writable": true,
          "signer": true
        },
        {
          "name": "admin",
          "writable": true,
          "signer": true
        },
        {
          "name": "system_program",
          "address": "11111111111111111111111111111111"
        }
      ],
      "args": []
    },
    {
      "name": "place_limit_order",
      "discriminator": [
        108,
        176,
        33,
        186,
        146,
        229,
        1,
        197
      ],
      "accounts": [
        {
          "name": "order_book",
          "writable": true
        },
        {
          "name": "trader",
          "signer": true
        }
      ],
      "args": [
        {
          "name": "side",
          "type": "u8"
        },
        {
          "name": "price",
          "type": "u64"
        },
        {
          "name": "quantity",
          "type": "u64"
        }
      ]
    }
  ],
  "accounts": [
    {
      "name": "OrderBookAccount",
      "discriminator": [
        109,
        71,
        76,
        82,
        184,
        138,
        162,
        171
      ]
    }
  ],
  "events": [
    {
      "name": "TradeEvent",
      "discriminator": [
        189,
        219,
        127,
        211,
        78,
        230,
        97,
        238
      ]
    }
  ],
  "types": [
    {
      "name": "Order",
      "type": {
        "kind": "struct",
        "fields": [
          {
            "name": "trader",
            "type": "pubkey"
          },
          {
            "name": "price",
            "type": "u64"
          },
          {
            "name": "quantity",
            "type": "u64"
          }
        ]
      }
    },
    {
      "name": "OrderBookAccount",
      "type": {
        "kind": "struct",
        "fields": [
          {
            "name": "bids",
            "type": {
              "vec": {
                "defined": {
                  "name": "Order"
                }
              }
            }
          },
          {
            "name": "asks",
            "type": {
              "vec": {
                "defined": {
                  "name": "Order"
                }
              }
            }
          }
        ]
      }
    },
    {
      "name": "TradeEvent",
      "type": {
        "kind": "struct",
        "fields": [
          {
            "name": "maker",
            "type": "pubkey"
          },
          {
            "name": "taker",
            "type": "pubkey"
          },
          {
            "name": "price",
            "type": "u64"
          },
          {
            "name": "quantity",
            "type": "u64"
          },
          {
            "name": "side",
            "type": "u8"
          }
        ]
      }
    }
  ]
}